gosnomer/__init__.py
gosnomer/gosnomer.py
gosnomer-0.0.9.dist-info/LICENSE
gosnomer-0.0.9.dist-info/METADATA
gosnomer-0.0.9.dist-info/WHEEL
gosnomer-0.0.9.dist-info/top_level.txt
gosnomer-0.0.9.dist-info/RECORD
