Metadata-Version: 2.1
Name: gosnomer
Version: 0.0.9
Summary: Исправление ручного ввода автомобильных номеров РФ
Home-page: https://github.com/leshchenko1979/gosnomer
Author: Alexey Leshchenko
Author-email: leshchenko@gmail.com
License: MIT
Classifier: Programming Language :: Python :: 3
Classifier: License :: OSI Approved :: MIT License
Classifier: Operating System :: OS Independent
Requires-Python: >=3.6
License-File: LICENSE
